pygelf4ovh/__init__.py
pygelf4ovh/pygelf4ovh.py
pygelf4ovh-0.4.dist-info/LICENSE
pygelf4ovh-0.4.dist-info/METADATA
pygelf4ovh-0.4.dist-info/WHEEL
pygelf4ovh-0.4.dist-info/top_level.txt
pygelf4ovh-0.4.dist-info/RECORD
