Metadata-Version: 2.1
Name: pygelf4ovh
Version: 0.4
Summary: pygelf adaptation that work for OVH Logs Data Platform
Home-page: https://github.com/olopost/pygelf4ovh
Author: Samuel MEYNARD
Author-email: samuel@meyn.fr
License: UNKNOWN
Platform: UNKNOWN
Classifier: Programming Language :: Python :: 3
Classifier: License :: OSI Approved :: MIT License
Classifier: Operating System :: OS Independent
Requires-Dist: pygelf
